quiltz/__init__.py
quiltz/testsupport/__init__.py
quiltz/testsupport/logging.py
quiltz/testsupport/probing.py
quiltz/testsupport/version.py
quiltz/testsupport/smtp/__init__.py
quiltz/testsupport/smtp/stub_smtp_server.py
quiltz/testsupport/smtp/pems/cert.pem
quiltz/testsupport/smtp/pems/key.pem
quiltz_testsupport-0.3.1.dist-info/LICENSE
quiltz_testsupport-0.3.1.dist-info/METADATA
quiltz_testsupport-0.3.1.dist-info/WHEEL
quiltz_testsupport-0.3.1.dist-info/top_level.txt
quiltz_testsupport-0.3.1.dist-info/RECORD
