Metadata-Version: 2.1
Name: quiltz-testsupport
Version: 0.3.1
Summary: A testsupport utility module for python
Home-page: https://github.com/qwaneu/quiltz-testsupport
Author: Rob Westgeest
Author-email: rob@qwan.eu
Classifier: Programming Language :: Python :: 3
Classifier: License :: OSI Approved :: MIT License
Classifier: Operating System :: OS Independent
License-File: LICENSE
Requires-Dist: pytest (~=7.2.0)
Requires-Dist: pyhamcrest (~=2.0.4)
Requires-Dist: aiosmtpd (==1.4.2)
